tuned/__init__.py
tuned/__main__.py
tuned/cli/__init__.py
tuned/cli/chord.py
tuned/cli/main.py
tuned/cli/metronome.py
tuned/cli/pulsed.py
tuned/cli/tuner.py
tuned/cli/display/__init__.py
tuned/cli/display/color.py
tuned/cli/display/tap_tempo.py
tuned/cli/display/terminal.py
tuned/metronome/__init__.py
tuned/metronome/clock.py
tuned/metronome/tick.py
tuned/midi/__init__.py
tuned/midi/controller.py
tuned/midi/midi_mapping.json
tuned/sound_analysis/__init__.py
tuned/sound_analysis/analyzer.py
tuned/sound_analysis/attack.py
tuned/sound_analysis/chord.py
tuned/sound_analysis/process.py
tuned/sound_analysis/strategies.py
tuned/sound_analysis/stream.py
tuned/sound_analysis/theory.py
tuned-0.6.1.dist-info/licenses/COPYING
tuned-0.6.1.dist-info/METADATA
tuned-0.6.1.dist-info/WHEEL
tuned-0.6.1.dist-info/entry_points.txt
tuned-0.6.1.dist-info/top_level.txt
tuned-0.6.1.dist-info/RECORD
