Metadata-Version: 2.4
Name: TunEd
Version: 0.6.1
Summary: Command line Tuner
Author-email: drd <drd.ltt000@gmail.com>
License-Expression: GPL-3.0-or-later
Project-URL: repository, https://framagit.org/drd/tuned
Keywords: python,audio,tuner,midi
Classifier: Programming Language :: Python :: 3.12
Classifier: Operating System :: POSIX :: Linux
Classifier: Environment :: Console
Classifier: Topic :: Terminals
Classifier: Topic :: Multimedia :: Sound/Audio
Classifier: Topic :: Multimedia :: Sound/Audio :: Analysis
Classifier: Topic :: Multimedia :: Sound/Audio :: Capture/Recording
Classifier: Topic :: Utilities
Requires-Python: >=3.12
License-File: COPYING
Requires-Dist: sounddevice==0.4.6
Requires-Dist: numpy==1.26.4
Requires-Dist: scipy==1.16.1
Requires-Dist: librosa==0.11.0
Requires-Dist: aubio==0.4.9
Requires-Dist: python-rtmidi==1.5.8
Requires-Dist: mido==1.3.3
Dynamic: license-file
